delta_robot_trampoline/__init__.py
delta_robot_trampoline-0.0.2.dist-info/DESCRIPTION.rst
delta_robot_trampoline-0.0.2.dist-info/METADATA
delta_robot_trampoline-0.0.2.dist-info/RECORD
delta_robot_trampoline-0.0.2.dist-info/WHEEL
delta_robot_trampoline-0.0.2.dist-info/metadata.json
delta_robot_trampoline-0.0.2.dist-info/top_level.txt
